tags_generator/__init__.py
tags_generator/tags_generator.py
tags_generator-0.4.0.dist-info/LICENSE
tags_generator-0.4.0.dist-info/METADATA
tags_generator-0.4.0.dist-info/WHEEL
tags_generator-0.4.0.dist-info/top_level.txt
tags_generator-0.4.0.dist-info/RECORD
