Metadata-Version: 2.1
Name: tags-generator
Version: 0.4.0
Summary: A library to generate tags list from a text using OpenAI
Home-page: https://github.com/nigohiroki/tags-generator
Author: nigohiroki
Author-email: nigohiroki@teit-inc.com
License: UNKNOWN
Platform: UNKNOWN
Classifier: Development Status :: 3 - Alpha
Classifier: Intended Audience :: Developers
Classifier: License :: OSI Approved :: MIT License
Classifier: Programming Language :: Python :: 3
Classifier: Programming Language :: Python :: 3.6
Classifier: Programming Language :: Python :: 3.7
Classifier: Programming Language :: Python :: 3.8
Classifier: Programming Language :: Python :: 3.9
License-File: LICENSE
Requires-Dist: openai
